datasaurus/__init__.py
datasaurus/core/__init__.py
datasaurus/core/loggers.py
datasaurus/core/models/__init__.py
datasaurus/core/models/base.py
datasaurus/core/models/columns.py
datasaurus/core/models/debug/TestTransformation.csv
datasaurus/core/models/exceptions.py
datasaurus/core/models/factory.py
datasaurus/core/models/transformation.py
datasaurus/core/storage/__init__.py
datasaurus/core/storage/azure.py
datasaurus/core/storage/base.py
datasaurus/core/storage/format.py
datasaurus/core/storage/mixins.py
datasaurus/core/storage/storage.py
datasaurus/core/utils/__init__.py
datasaurus-0.0.2.dev4.dist-info/METADATA
datasaurus-0.0.2.dev4.dist-info/WHEEL
datasaurus-0.0.2.dev4.dist-info/RECORD
