Metadata-Version: 2.1
Name: datasaurus
Version: 0.0.2.dev4
Summary: Data Engineering framework based on Polars.rs
Home-page: https://www.github.com/surister/datasaurus
License: MIT
Keywords: python3,data,polars,dataframes,framework,data engineering
Author: surister
Author-email: surister98@gmail.com
Requires-Python: >=3.8.1,<4.0.0
Classifier: Development Status :: 2 - Pre-Alpha
Classifier: License :: OSI Approved :: MIT License
Classifier: Programming Language :: Python :: 3
Classifier: Programming Language :: Python :: 3.9
Classifier: Programming Language :: Python :: 3.10
Classifier: Programming Language :: Python :: 3.11
Classifier: Topic :: Software Development :: Libraries
Requires-Dist: connectorx (>=0.3.1,<0.4.0) ; python_version >= "3.8" and python_version < "4.0"
Requires-Dist: connectorx (>=0.3.2a6,<0.4.0) ; python_version >= "3.11" and python_version < "4.0"
Requires-Dist: deltalake (>=0.10.0,<0.11.0)
Requires-Dist: pandas (>=2.0.2,<3.0.0)
Requires-Dist: polars (>=0.20.1,<0.21.0)
Requires-Dist: pyarrow (>=12.0.0,<13.0.0)
Requires-Dist: sqlalchemy (>=2.0.15,<3.0.0)
Project-URL: Repository, https://www.github.com/surister/datasaurus
